{
  "Queue": "arn:aws:mediaconvert:us-east-1:576758376358:queues/Default",
  "UserMetadata": {},
  "Role": "arn:aws:iam::576758376358:role/service-role/MediaConvert_Default_Role",
  "Settings": {
    "TimecodeConfig": {
      "Source": "ZEROBASED"
    },
    "OutputGroups": [{
      "Name": "File Group",
      "Outputs": [{
        "ContainerSettings": {
          "Container": "MP4",
          "Mp4Settings": {}
        },
        "VideoDescription": {
          "CodecSettings": {
            "Codec": "H_264",
            "H264Settings": {
              "MaxBitrate": 12000000,
              "RateControlMode": "QVBR",
              "SceneChangeDetect": "TRANSITION_DETECTION"
            }
          }
        },
        "AudioDescriptions": [{
          "CodecSettings": {
            "Codec": "AAC",
            "AacSettings": {
              "Bitrate": 96000,
              "CodingMode": "CODING_MODE_2_0",
              "SampleRate": 48000
            }
          }
        }],
        "NameModifier": "-crop"
      }],
      "OutputGroupSettings": {
        "Type": "FILE_GROUP_SETTINGS",
        "FileGroupSettings": {
          "Destination": "s3://"
        }
      }
    }],
    "Inputs": [{
      "AudioSelectors": {
        "Audio Selector 1": {
          "DefaultSelection": "DEFAULT"
        }
      },
      "VideoSelector": {},
      "TimecodeSource": "ZEROBASED",
      "Crop": {
        "Height": "**h**",
        "Width": "**w**",
        "X": "**x**",
        "Y": "**y**"
      },
      "FileInput": "s3://**input_bucket**/**filename**"
    }]
  },
  "AccelerationSettings": {
    "Mode": "DISABLED"
  },
  "StatusUpdateInterval": "SECONDS_60",
  "Priority": 0
}